odoo/addons/reports_font_size/README.rst
odoo/addons/reports_font_size/__init__.py
odoo/addons/reports_font_size/__manifest__.py
odoo/addons/reports_font_size/data/report_layout.xml
odoo/addons/reports_font_size/i18n/es.po
odoo/addons/reports_font_size/models/__init__.py
odoo/addons/reports_font_size/models/base_document_layout.py
odoo/addons/reports_font_size/models/res_company.py
odoo/addons/reports_font_size/readme/CONFIGURE.md
odoo/addons/reports_font_size/readme/CONTRIBUTORS.md
odoo/addons/reports_font_size/readme/DESCRIPTION.md
odoo/addons/reports_font_size/readme/ROADMAP.md
odoo/addons/reports_font_size/readme/USAGE.md
odoo/addons/reports_font_size/static/description/icon.png
odoo/addons/reports_font_size/static/description/index.html
odoo/addons/reports_font_size/templates/report_style_templates.xml
odoo/addons/reports_font_size/tests/__init__.py
odoo/addons/reports_font_size/tests/test_reports_font_size.py
odoo/addons/reports_font_size/views/base_document_layout.xml
odoo_addon_reports_font_size-17.0.2.0.0.dist-info/METADATA
odoo_addon_reports_font_size-17.0.2.0.0.dist-info/WHEEL
odoo_addon_reports_font_size-17.0.2.0.0.dist-info/top_level.txt
odoo_addon_reports_font_size-17.0.2.0.0.dist-info/RECORD
