Metadata-Version: 2.1
Name: odoo-addon-reports_font_size
Version: 17.0.2.0.0
Requires-Python: >=3.10
Requires-Dist: odoo>=17.0a,<17.1dev
Summary: Change reports font size from the document layout configurator
Home-page: https://github.com/sygel-technology/sy-server-backend
License: AGPL-3
Author: Sygel, Odoo Community Association (OCA)
Author-email: support@odoo-community.org
Classifier: Programming Language :: Python
Classifier: Framework :: Odoo
Classifier: Framework :: Odoo :: 17.0
Classifier: License :: OSI Approved :: GNU Affero General Public License v3
